---
source: crates/codegen/src/compile.rs
expression: "compile_exec(\"\\\nasync def test():\n    for stop_exc in (StopIteration('spam'), StopAsyncIteration('ham')):\n        with self.subTest(type=type(stop_exc)):\n            try:\n                async with egg():\n                    raise stop_exc\n            except Exception as ex:\n                self.assertIs(ex, stop_exc)\n            else:\n                self.fail(f'{stop_exc} was suppressed')\n\")"
---
  1           0 RESUME               (0)
              1 LOAD_CONST           (<code object test at ??? file "source_path", line 1>):  1               0 RETURN_GENERATOR
                  1 POP_TOP
            >>    2 RESUME               (0)

  2         >>    3 LOAD_GLOBAL          (0, StopIteration)
            >>    4 CACHE
            >>    5 CACHE
                  6 CACHE
                  7 CACHE
                  8 PUSH_NULL
                  9 LOAD_CONST           ("spam")
            >>   10 CALL                 (1)
                 11 CACHE
                 12 CACHE
                 13 CACHE
                 14 LOAD_GLOBAL          (1, StopAsyncIteration)
                 15 CACHE
                 16 CACHE
                 17 CACHE
            >>   18 CACHE
                 19 PUSH_NULL
                 20 LOAD_CONST           ("ham")
                 21 CALL                 (1)
                 22 CACHE
                 23 CACHE
                 24 CACHE
                 25 BUILD_TUPLE          (2)
                 26 GET_ITER
            >>   27 FOR_ITER             (73)
            >>   28 CACHE
                 29 STORE_FAST           (0, stop_exc)

  3              30 LOAD_GLOBAL          (2, self)
                 31 CACHE
                 32 CACHE
                 33 CACHE
            >>   34 CACHE
                 35 LOAD_ATTR            (7, subTest, method=true)
                 36 CACHE
                 37 CACHE
                 38 CACHE
                 39 CACHE
                 40 CACHE
                 41 CACHE
                 42 CACHE
                 43 CACHE
                 44 CACHE
                 45 LOAD_GLOBAL          (4, type)
                 46 CACHE
            >>   47 CACHE
                 48 CACHE
                 49 CACHE
                 50 PUSH_NULL
                 51 LOAD_FAST            (0, stop_exc)
                 52 CALL                 (1)
                 53 CACHE
                 54 CACHE
                 55 CACHE
                 56 LOAD_CONST           (("type"))
                 57 CALL_KW              (1)
                 58 CACHE
                 59 CACHE
                 60 CACHE
                 61 COPY                 (1)
                 62 LOAD_SPECIAL         (__exit__)
                 63 SWAP                 (2)
                 64 LOAD_SPECIAL         (__enter__)
                 65 PUSH_NULL
                 66 CALL                 (0)
                 67 CACHE
                 68 CACHE
                 69 CACHE
                 70 POP_TOP

  4              71 NOP

  5              72 LOAD_GLOBAL          (5, egg)
            >>   73 CACHE
                 74 CACHE
                 75 CACHE
                 76 CACHE
                 77 PUSH_NULL
                 78 CALL                 (0)
                 79 CACHE
                 80 CACHE
                 81 CACHE
                 82 COPY                 (1)
                 83 LOAD_SPECIAL         (__aexit__)
                 84 SWAP                 (2)
                 85 LOAD_SPECIAL         (__aenter__)
                 86 PUSH_NULL
                 87 CALL                 (0)
                 88 CACHE
                 89 CACHE
                 90 CACHE
                 91 GET_AWAITABLE        (1)
                 92 LOAD_CONST           (None)
                 93 SEND                 (3)
                 94 CACHE
                 95 YIELD_VALUE          (1)
                 96 RESUME               (3)
                 97 JUMP_BACKWARD_NO_INTERRUPT(5)
                 98 END_SEND
                 99 POP_TOP

  6             100 LOAD_FAST            (0, stop_exc)
                101 RAISE_VARARGS        (Raise)

  2             102 END_FOR
                103 POP_ITER
                104 LOAD_CONST           (None)
                105 RETURN_VALUE

  5             106 CLEANUP_THROW
                107 JUMP_BACKWARD_NO_INTERRUPT(10)

  6             108 NOP

  5             109 PUSH_NULL
                110 LOAD_CONST           (None)
                111 LOAD_CONST           (None)
                112 LOAD_CONST           (None)
                113 CALL                 (3)
                114 CACHE
                115 CACHE
                116 CACHE
                117 GET_AWAITABLE        (2)
                118 LOAD_CONST           (None)
                119 SEND                 (4)
                120 CACHE
                121 YIELD_VALUE          (1)
                122 RESUME               (3)
                123 JUMP_BACKWARD_NO_INTERRUPT(5)
                124 CLEANUP_THROW
                125 END_SEND
                126 POP_TOP
                127 JUMP_FORWARD         (27)
                128 PUSH_EXC_INFO
                129 WITH_EXCEPT_START
                130 GET_AWAITABLE        (2)
                131 LOAD_CONST           (None)
                132 SEND                 (4)
                133 CACHE
                134 YIELD_VALUE          (1)
                135 RESUME               (3)
                136 JUMP_BACKWARD_NO_INTERRUPT(5)
                137 CLEANUP_THROW
                138 END_SEND
                139 TO_BOOL
                140 CACHE
                141 CACHE
                142 CACHE
                143 POP_JUMP_IF_TRUE     (2)
                144 CACHE
                145 NOT_TAKEN
                146 RERAISE              (2)
                147 POP_TOP
                148 POP_EXCEPT
                149 POP_TOP
                150 POP_TOP
                151 JUMP_FORWARD         (3)
                152 COPY                 (3)
                153 POP_EXCEPT
                154 RERAISE              (1)
                155 JUMP_FORWARD         (47)
                156 PUSH_EXC_INFO

  7             157 LOAD_GLOBAL          (6, Exception)
                158 CACHE
                159 CACHE
                160 CACHE
                161 CACHE
                162 CHECK_EXC_MATCH
                163 POP_JUMP_IF_FALSE    (34)
                164 CACHE
                165 NOT_TAKEN
                166 STORE_FAST           (1, ex)

  8             167 LOAD_GLOBAL          (2, self)
                168 CACHE
                169 CACHE
                170 CACHE
                171 CACHE
                172 LOAD_ATTR            (15, assertIs, method=true)
                173 CACHE
                174 CACHE
                175 CACHE
                176 CACHE
                177 CACHE
                178 CACHE
                179 CACHE
                180 CACHE
                181 CACHE
                182 LOAD_FAST            (1, ex)
                183 LOAD_FAST            (0, stop_exc)
                184 CALL                 (2)
                185 CACHE
                186 CACHE
                187 CACHE
                188 POP_TOP
                189 JUMP_FORWARD         (4)
                190 LOAD_CONST           (None)
                191 STORE_FAST           (1, ex)
                192 DELETE_FAST          (1, ex)
                193 RAISE_VARARGS        (ReraiseFromStack)
                194 POP_EXCEPT
                195 LOAD_CONST           (None)
                196 STORE_FAST           (1, ex)
                197 DELETE_FAST          (1, ex)
                198 JUMP_FORWARD         (28)
                199 RAISE_VARARGS        (ReraiseFromStack)
                200 COPY                 (3)
                201 POP_EXCEPT
                202 RAISE_VARARGS        (ReraiseFromStack)

 10             203 LOAD_GLOBAL          (2, self)
                204 CACHE
                205 CACHE
                206 CACHE
                207 CACHE
                208 LOAD_ATTR            (17, fail, method=true)
                209 CACHE
                210 CACHE
                211 CACHE
                212 CACHE
                213 CACHE
                214 CACHE
                215 CACHE
                216 CACHE
                217 CACHE
                218 LOAD_FAST_BORROW     (0, stop_exc)
                219 FORMAT_SIMPLE
                220 LOAD_CONST           (" was suppressed")
                221 BUILD_STRING         (2)
                222 CALL                 (1)
                223 CACHE
                224 CACHE
                225 CACHE
                226 POP_TOP
                227 NOP

  3             228 PUSH_NULL
                229 LOAD_CONST           (None)
                230 LOAD_CONST           (None)
            >>  231 LOAD_CONST           (None)
                232 CALL                 (3)
                233 CACHE
                234 CACHE
                235 CACHE
                236 POP_TOP
                237 JUMP_FORWARD         (18)
                238 PUSH_EXC_INFO
                239 WITH_EXCEPT_START
                240 TO_BOOL
                241 CACHE
                242 CACHE
                243 CACHE
                244 POP_JUMP_IF_TRUE     (2)
                245 CACHE
                246 NOT_TAKEN
                247 RERAISE              (2)
                248 POP_TOP
                249 POP_EXCEPT
                250 POP_TOP
                251 POP_TOP
                252 JUMP_FORWARD         (3)
                253 COPY                 (3)
                254 POP_EXCEPT
                255 RERAISE              (1)
                256 JUMP_BACKWARD        (231)
                257 CACHE

              2 MAKE_FUNCTION
              3 STORE_NAME           (0, test)
              4 LOAD_CONST           (None)
              5 RETURN_VALUE
